autohooks/plugins/ruff/__init__.py
autohooks/plugins/ruff/__version__.py
autohooks/plugins/ruff/check.py
autohooks/plugins/ruff/format.py
autohooks/plugins/ruff/utils.py
autohooks_plugin_ruff-25.3.1.dist-info/LICENSE
autohooks_plugin_ruff-25.3.1.dist-info/METADATA
autohooks_plugin_ruff-25.3.1.dist-info/WHEEL
autohooks_plugin_ruff-25.3.1.dist-info/RECORD
