Metadata-Version: 2.3
Name: autohooks-plugin-ruff
Version: 25.3.1
Summary: An autohooks plugin for python code formatting via ruff
License: GPL-3.0-or-later
Keywords: git,formatting,linting,hooks,ruff
Author: Greenbone AG
Author-email: info@greenbone.net
Requires-Python: >=3.9,<4.0
Classifier: Development Status :: 5 - Production/Stable
Classifier: Environment :: Console
Classifier: Intended Audience :: Developers
Classifier: License :: OSI Approved :: GNU General Public License v3 or later (GPLv3+)
Classifier: Operating System :: OS Independent
Classifier: Programming Language :: Python :: 3
Classifier: Programming Language :: Python :: 3.9
Classifier: Programming Language :: Python :: 3.10
Classifier: Programming Language :: Python :: 3.11
Classifier: Programming Language :: Python :: 3.12
Classifier: Programming Language :: Python :: 3.13
Classifier: Topic :: Software Development :: Libraries :: Python Modules
Requires-Dist: autohooks (>=25.2.0)
Requires-Dist: ruff (>=0.0.272)
Project-URL: Homepage, https://github.com/greenbone/autohooks-plugin-ruff
Project-URL: Repository, https://github.com/greenbone/autohooks-plugin-ruff
